Ace_todolist/__init__.py
Ace_todolist/__main__.py
Ace_todolist/add_todo.py
Ace_todolist/create_db.py
Ace_todolist/detail.py
Ace_todolist/edit_todo.py
Ace_todolist/input_check.py
Ace_todolist/list_todo.py
Ace_todolist/now_date.py
Ace_todolist/remove_todo.py
Ace_todolist/search.py
Ace_todolist/setup.py
Ace_todolist/stat_todo.py
Ace_todolist-2.1.dist-info/METADATA
Ace_todolist-2.1.dist-info/RECORD
Ace_todolist-2.1.dist-info/WHEEL
Ace_todolist-2.1.dist-info/entry_points.txt
Ace_todolist-2.1.dist-info/top_level.txt
